evepaste/__init__.py
evepaste/exceptions.py
evepaste/utils.py
evepaste/parsers/__init__.py
evepaste/parsers/assets.py
evepaste/parsers/bill_of_materials.py
evepaste/parsers/cargo_scan.py
evepaste/parsers/chat.py
evepaste/parsers/contract.py
evepaste/parsers/dscan.py
evepaste/parsers/eft.py
evepaste/parsers/fitting.py
evepaste/parsers/industry.py
evepaste/parsers/killmail.py
evepaste/parsers/listing.py
evepaste/parsers/loot_history.py
evepaste/parsers/pi.py
evepaste/parsers/survey_scanner.py
evepaste/parsers/view_contents.py
evepaste/parsers/wallet.py
evepaste-0.9.dist-info/DESCRIPTION.rst
evepaste-0.9.dist-info/METADATA
evepaste-0.9.dist-info/metadata.json
evepaste-0.9.dist-info/RECORD
evepaste-0.9.dist-info/top_level.txt
evepaste-0.9.dist-info/WHEEL
