Metadata-Version: 2.0
Name: evepaste
Version: 0.9
Summary: A Python library to help parse various things that are copy/pastable from the Eve Online UI.
Home-page: UNKNOWN
Author: Kevin McDonald
Author-email: k3vinmcdonald@gmail.com
License: MIT
Platform: UNKNOWN
